pbtools/version.py
pbtools/__init__.py
pbtools/__main__.py
pbtools/parser.py
pbtools/errors.py
pbtools/c_source/__init__.py
pbtools/subparsers/__init__.py
pbtools/subparsers/generate_c_source.py
pbtools-0.36.0.dist-info/RECORD
pbtools-0.36.0.dist-info/metadata.json
pbtools-0.36.0.dist-info/entry_points.txt
pbtools-0.36.0.dist-info/DESCRIPTION.rst
pbtools-0.36.0.dist-info/top_level.txt
pbtools-0.36.0.dist-info/WHEEL
pbtools-0.36.0.dist-info/METADATA
