Metadata-Version: 2.0
Name: pbtools
Version: 0.36.0
Summary: Google Protocol Buffers tools.
Home-page: https://github.com/eerimoq/pbtools
Author: Erik Moqvist
Author-email: erik.moqvist@gmail.com
License: MIT
Keywords: protobuf,proto,protocol buffers
Platform: UNKNOWN
Classifier: License :: OSI Approved :: MIT License
Classifier: Programming Language :: Python :: 3
Requires-Dist: textparser (>=0.21.1)
